Workbook

Sheet 0_Definitions
A1: Green Sight AI — TAM / SAM / SOM Market Sizing Workbook
A3: Field | B3: Content
A4: Course | B4: ENT303TC Team Technopreneurship | S1 W3 Market & Competitor Analysis
A5: Venture | B5: Green Sight AI - continuing prototype; no paid revenue and no observed paid conversion rate.
A6: Date | B6: 2026-09-23
A7: Version | B7: v4 - user-supplied evidence; sourced assumptions and validation plan
A8: Unit | B8: All money figures in CNY unless labelled USD
A9: Method | B9: Top-down chain TAM → SAM → SOM with visible Excel formulas; bottom-up sanity check; 1%/2%/3% SOM sensitivity
A10: Product definition for sizing | B10: Busy urban indoor-pot users: students and young office workers in dorms, apartments and at office desks. Multi-sensor monitoring + App + basic automatic intervention; mostly single-threshold control. Prototype, not mature AI. Greenhouses, vertical farms and closed consumable grower ecosystems are outside the primary scope.
A11: TAM definition | B11: China smart-planter market, including indoor and outdoor uses; proxy for adjacent plant-care hardware, not a direct measurement of retrofit care devices. 2024 market baseline.
A12: SAM definition | B12: Share of TAM matching our ICP (busy students / young professionals with dorm/apartment/office desk pots) AND reachable via Year-1 GTM channels (campus pilots + Xiaohongshu/Taobao e-commerce in campus cities).
A13: SOM definition | B13: Year-1 SOM approx. CNY323,000 / approx. 809 units at a CNY399 reference ASP is a planning scenario, NOT realised sales. The price is a competitor-band reference, not our confirmed selling price. Uses a 2024 market baseline; reach and capture assumptions remain UNVERIFIED.
A14: Colour key | B14: Yellow = editable inputs; green = executable calculation cells; grey = formula text for reference (not executable). Formula text must be updated if the calculation formula changes.
... A16: Honesty rule | B16: External claims use only sources provided by the user. This revision performs no new web verification. All future operating estimates are Assumption / UNVERIFIED; no interviews, sales, conversion records or partnerships are claimed.

Sheet 1_Assumptions
A1: ID | B1: Parameter | C1: Value | D1: Unit | E1: Role | F1: Source / rationale | G1: URL | H1: Confidence | I1: How to validate / 验证方法
A2: A01 | B2: China Smart Planters market size in 2030 (forecast) | C2: 87.1 | D2: USD million | E2: TAM input | F2: User-supplied external evidence: GIA/GII China 2030 forecast US$87.1M. Public abstract only; smart-planter category proxy. | G2: https://www.giiresearch.com/report/go1739256-smart-planters.html | H2: Medium (paid report abstract publicly cited) | I2: Confirm source scope and retain abstract/report citation; replace proxy if directly comparable retrofit-device data is provided.
A3: A02 | B3: CAGR China Smart Planters 2024-2030 | C3: 0.053 | D3: decimal | E3: TAM input | F3: User-supplied external evidence: China 2024-2030 CAGR 5.3%. Forecast assumption from source, not realised growth. | G3: https://www.giiresearch.com/report/go1739256-smart-planters.html | H3: Medium | I3: Retain forecast period; do not present CAGR as measured Green Sight growth.
A4: A03 | B4: Years from 2024 to 2030 | C4: 6 | D4: years | E4: TAM input | F4: Arithmetic: 2030-2024=6. Used to back-calculate 2024 from 2030 forecast. | G4: Derived | H4: High | I4: Arithmetic check: 2030 - 2024 = 6.
A5: A04 | B5: FX USD to CNY (workbook assumption) | C5: 7.2 | D5: CNY per USD | E5: TAM input | F5: Assumption / UNVERIFIED: 7.2 CNY per USD used as a classroom conversion convention, not a current FX quote. | G5: Team assumption — label UNVERIFIED for live FX | H5: Assumption / UNVERIFIED | I5: Replace with a dated, approved FX source when supplied; test 7.0-7.3 as assumptions.
A6: A05 | B6: Share of smart-planter spend that is indoor / residential-like | C6: 0.65 | D6: decimal | E6: SAM input | F6: Assumption / UNVERIFIED: 65% indoor share used as a provisional scenario because our use cases are indoor. Source segment labels establish categories, not this percentage. | G6: https://www.giiresearch.com/report/go1739256-smart-planters.html (segment exists; % UNVERIFIED) | H6: Assumption / UNVERIFIED | I6: Obtain China indoor/outdoor device revenue split, or a defined device-buyer sample with spending weights.
A7: A06 | B7: ICP share of indoor smart-planter spending | C7: 0.45 | D7: decimal | E7: SAM input | F7: Assumption / UNVERIFIED: 45% of indoor device spend assigned to student/young-worker desk-pot use. JD buyer descriptions support ICP direction only, not this share. | G7: http://www.xfrb.com.cn/article/council/16452445152521.html (ICP context only; 45% is not sourced) | H7: Assumption / UNVERIFIED | I7: Survey smart-care device buyers: age, desk-pot use and annual spending; report sample size and selection bias.
A8: A07 | B8: Reachable share of ICP smart-planter spending | C8: 0.12 | D8: decimal | E8: SAM input | F8: Assumption / UNVERIFIED: 12% of ICP spending provisionally reachable through campus pilots, Xiaohongshu and Taobao/JD in selected campus cities. National offline flower retail is excluded. No channel access or exposure is claimed as achieved. | G8: Planning assumption; named channels are a route hypothesis, not verified coverage. | H8: Assumption / UNVERIFIED | I8: Name pilot campuses/cities and channels; record unique eligible reach and spending potential; deduplicate across channels.
A9: A08 | B9: Year-1 revenue capture share of reachable market | C9: 0.02 | D9: decimal | E9: SOM input | F9: Assumption / UNVERIFIED: 2% baseline, tested at 1% and 3%. Prototype maturity, low-priced irrigators/self-watering pots and a more productised Yimitian support cautious planning, but do not establish the numerical rate. Revenue capture share is not customer conversion. | G9: User-supplied competitor references: 5_Sources rows 9-11. Qualitative rationale only. | H9: Assumption / UNVERIFIED | I9: Run a consented paid pilot; record eligible leads, orders, price, refunds and delivery limits; infer revenue/SAM.
A10: A09 | B10: Reference ASP - low end of Yimitian-like comparison band | C10: 399 | D10: CNY / unit | E10: Display only | F10: User-supplied third-party reference band CNY399-499; use 399 solely to translate revenue to illustrative units. Channel-dependent, not an official verified current quote or Green Sight price. | G10: http://www.ymitian.cn/chanpin4/91.html | H10: Medium / price caution | I10: Collect dated seller quotes for comparable functions; validate our price separately with willingness-to-pay and costs.
A11: A10 | B11: CONTEXT ONLY — China indoor foliage plant market 2024 | C11: 135 | D11: CNY 100 million (亿元) | E11: Context (NOT used in TAM formula) | F11: China Flower Association / national forestry portal summary: foliage plant market ~¥13.5B in 2024; tropical/specialty ~30%. | G11: https://www.forestry.gov.cn/lyj/1/gghhmmcy/20250328/617790.html | H11: High (association-linked) | I11: Context only; not linked to device TAM.
A12: A11 | B12: CONTEXT ONLY — China flower retail market 2024 | C12: 2200 | D12: CNY 100 million (亿元) | E12: Context | F12: China Flower Association retail branch: national flower retail ~¥220B in 2024; e-commerce ~¥120B (54.5%). | G12: https://www.chinahhxh.com/hhxh/magazineNewsDetail.html?contentId=1234&id=73&subCategoryId=15 | H12: High | I12: Context only; online flower sales do not prove our reach.
A13: A12 | B13: CONTEXT — China indoor plants market 2024 (Beizhes via Gelonghui) | C13: 222.23 | D13: CNY 100 million (亿元) | E13: Context / alternate ceiling | F13: Beizhes Consulting cited on Gelonghui: China indoor plants market ¥22.223B in 2024. Broader than foliage-only; NOT our device TAM. | G13: https://www.gelonghui.com/p/2427468 | H13: Medium (secondary cite of paid research) | I13: Secondary citation; broader plant category, not device TAM.
... A18: B05 | B18: Bottom-up: Year-1 capture among reachable plant owners | C18: 0.015 | D18: decimal | E18: Bottom-up SOM | F18: Assumption / UNVERIFIED: 1.5% of reachable student plant owners become paid buyers, one unit each. No observed conversion history. This direct conversion already includes willingness to buy; do not also multiply by 8%. | G18: Team assumption; paid pilot / comparable conversion evidence required | H18: Assumption / UNVERIFIED | I18: Observe paid units / unique reachable plant owners over a stated period; one-unit-per-buyer assumption.
A21: Optional validation | B21: Named campuses / cities | C21: Unique people reached | D21: Eligible ICP share | E21: Paid conversion per eligible person | F21: Expected paid units | G21: Evidence / dates / deduplication | H21: Owner / due
A22: Campus pilots | F22: =IF(COUNT(C22:E22)<3,"",C22*D22*E22) | G22: Unique audience after cross-channel deduplication; eligible = target plant owners. Conversion denominator is eligible people; assume one device per paid buyer. Record source and dates.
A23: Xiaohongshu | F23: =IF(COUNT(C23:E23)<3,"",C23*D23*E23) | G23: Unique audience after cross-channel deduplication; eligible = target plant owners. Conversion denominator is eligible people; assume one device per paid buyer. Record source and dates.
A24: Taobao / JD | F24: =IF(COUNT(C24:E24)<3,"",C24*D24*E24) | G24: Unique audience after cross-channel deduplication; eligible = target plant owners. Conversion denominator is eligible people; assume one device per paid buyer. Record source and dates.
A25: Additional channel | F25: =IF(COUNT(C25:E25)<3,"",C25*D25*E25) | G25: Unique audience after cross-channel deduplication; eligible = target plant owners. Conversion denominator is eligible people; assume one device per paid buyer. Record source and dates.
A26: Total forecast | C26: =IF(COUNT(C22:C25)<4,"",SUM(C22:C25)) | F26: =IF(COUNT(F22:F25)<4,"",SUM(F22:F25)) | G26: Optional future validation block: blank inputs are intentional, not actual operating data. Main TAM/SAM/SOM scenario remains complete.
A29: Delivery check | B29: Input / meaning | C29: Value | D29: Unit | E29: Role | F29: Evidence required | G29: Source / status | H29: Owner / due
A30: P01 | B30: Units that can be built and delivered in first 12 months | D30: units | E30: Capacity | F30: Supplier quote, lead times, testing and team capacity. | G30: =IF(ISNUMBER(C30),"Input supplied; evidence still required","Missing input") -> Missing input
A31: P02 | B31: Proposed net realised selling price | D31: CNY / unit | E31: Price | F31: Customer willingness-to-pay and discount/refund assumptions. | G31: =IF(ISNUMBER(C31),"Input supplied; evidence still required","Missing input") -> Missing input
A32: P03 | B32: Capacity-limited forecast units | C32: =IF(AND(ISNUMBER(F26),ISNUMBER(C30)),MIN(F26,C30),"") | D32: units | E32: Calculation | F32: Minimum of channel demand and delivery capacity. | G32: =IF(ISNUMBER(C32),"Calculated scenario; evidence still required","Pending required inputs") -> Pending required inputs
A33: P04 | B33: Capacity-limited forecast revenue | C33: =IF(AND(ISNUMBER(C32),ISNUMBER(C31)),C32*C31,"") | D33: CNY / 12 months | E33: Calculation | F33: Forecast units x proposed net price; replaces neither scenario until supported. | G33: =IF(ISNUMBER(C33),"Calculated scenario; evidence still required","Pending required inputs") -> Pending required inputs

Sheet 2_TAM_SAM_SOM_Chain
A1: MARKET SCENARIO - 2024 baseline; first-12-month capture assumptions unvalidated
A3: Layer | B3: Calculation (plain English) | C3: Formula text (update if formula edited) | D3: Result | E3: Unit | F3: Source IDs used | G3: Notes for supervisor challenge
A4: TAM (step 1) | B4: Back-calculate China Smart Planters 2024 USD from 2030 forecast using CAGR | C4: ='1_Assumptions'!C2/((1+'1_Assumptions'!C3)^'1_Assumptions'!C4) | D4: ='1_Assumptions'!C2/((1+'1_Assumptions'!C3)^'1_Assumptions'!C4) -> 63.892213 | E4: USD million | F4: A01, A02, A03 | G4: Derived 2024 baseline, not an observed 2026 value. GII public abstract checked 2026-09-23.
A5: TAM (step 2) | B5: Convert TAM USD → CNY | C5: =D4*'1_Assumptions'!C5 | D5: =D4*'1_Assumptions'!C5 -> 460.02393 | E5: CNY million | F5: A04 | G5: FX is a yellow assumption. Also show ¥亿元 below.
A6: TAM (display) | B6: TAM in 亿元 for slide friendliness | C6: =D5/100 | D6: =D5/100 -> 4.6002393 | E6: CNY 亿元 | F6: — | G6: This is DEVICE market proxy, NOT the ¥135亿 foliage plant market.
A7: SAM | B7: TAM × indoor share × ICP fit × Year-1 channel reach | C7: =D5*'1_Assumptions'!C6*'1_Assumptions'!C7*'1_Assumptions'!C8 | D7: =D5*'1_Assumptions'!C6*'1_Assumptions'!C7*'1_Assumptions'!C8 -> 16.14684 | E7: CNY million | F7: A05, A06, A07 | G7: 65% indoor x 45% ICP x 12% reach: all unvalidated. Report as a scenario.
A8: SAM (display) | B8: SAM in 亿元 | C8: =D7/100 | D8: =D7/100 -> 0.1614684 | E8: CNY 亿元 | F8: —
A9: SOM (Year-1) | B9: SAM × Year-1 capture rate | C9: =D7*'1_Assumptions'!C9 | D9: =D7*'1_Assumptions'!C9 -> 0.3229368 | E9: CNY million | F9: A08 | G9: Assumption / UNVERIFIED: active capture rate; 1% / 2% / 3% sensitivity on sheet 3.
A10: SOM (display) | B10: SOM in CNY (absolute yuan) | C10: =D9*1000000 | D10: =D9*1000000 -> 322936.8 | E10: CNY | F10: — | G10: Scenario revenue, not a validated sales forecast.
A11: SOM units (illustrative) | B11: SOM CNY ÷ reference ASP | C11: =D10/'1_Assumptions'!C10 | D11: =D10/'1_Assumptions'!C10 -> 809.36541 | E11: units / year | F11: A09 | G11: Illustrative only — ASP is competitor band, not our final price.
A13: Method and evidence limitations
A14: TAM uses the China smart-planter market (indoor + outdoor) as an adjacent-category proxy. SAM applies unvalidated indoor, ICP and reach filters. SOM applies an unvalidated first-year capture assumption to a 2024 market baseline. A launch-year estimate requires a supported update; no 2026 uplift is assumed.
A16: What this is NOT
A17: Do NOT present the ¥135亿 indoor foliage market or ¥2200亿 flower retail market as our TAM. Those measure plant/flower spend, not smart care devices. They are CONTEXT that demand for indoor plants (and therefore care pain) is large.
A19: Optional validation | B19: Future channel validation; not required to calculate the scenario above
A20: Demand units | B20: From completed channel inputs | C20: =IF(ISNUMBER('1_Assumptions'!F26),'1_Assumptions'!F26,"Pending inputs") | D20: =IF(ISNUMBER('1_Assumptions'!F26),'1_Assumptions'!F26,"Pending inputs") -> Pending inputs | E20: units | G20: Pending until all channel inputs are supplied.
A21: Deliverable units | B21: Minimum of demand and delivery capacity | C21: =IF(ISNUMBER('1_Assumptions'!C32),'1_Assumptions'!C32,"Pending inputs") | D21: =IF(ISNUMBER('1_Assumptions'!C32),'1_Assumptions'!C32,"Pending inputs") -> Pending inputs | E21: units | G21: Assumes one unit per paid buyer.
A22: Revenue | B22: Deliverable units x proposed net selling price | C22: =IF(ISNUMBER('1_Assumptions'!C33),'1_Assumptions'!C33,"Pending inputs") | D22: =IF(ISNUMBER('1_Assumptions'!C33),'1_Assumptions'!C33,"Pending inputs") -> Pending inputs | E22: CNY | G22: Not automatically a verified target. Evidence required.
A23: Implied share | B23: Channel forecast revenue / SAM | C23: =IF(AND(ISNUMBER(D22),D7>0),D22/(D7*1000000),"Pending inputs") | D23: =IF(AND(ISNUMBER(D22),D7>0),D22/(D7*1000000),"Pending inputs") -> Pending inputs | E23: share of SAM | G23: Compare with original capture assumption; do not treat as customer conversion.
A24: Interpretation | B24: 渠道预测与原有比例情景分别列示。填完输入后此区自动更新；没有证据时不自动替换2%假设，也不声称已消除两种估算的差异。

Sheet 3_SOM_Sensitivity
A1: SOM sensitivity — supervisor often challenges capture rate
A3: Scenario | B3: Capture rate | C3: SOM (CNY million) | D3: SOM (CNY) | E3: Illustrative units @ ASP | F3: When to use
A4: Conservative | B4: 0.01 | C4: ='2_TAM_SAM_SOM_Chain'!D7*B4 -> 0.1614684 | D4: =C4*1000000 -> 161468.4 | E4: =D4/'1_Assumptions'!C10 -> 404.68271 | F4: Strong incumbent / weak willingness-to-pay evidence
A5: Base (workbook) | B5: ='1_Assumptions'!C9 -> 0.02 | C5: ='2_TAM_SAM_SOM_Chain'!D7*B5 -> 0.3229368 | D5: =C5*1000000 -> 322936.8 | E5: =D5/'1_Assumptions'!C10 -> 809.36541 | F5: Linked to the main assumption; remains unvalidated.
A6: Optimistic | B6: 0.03 | C6: ='2_TAM_SAM_SOM_Chain'!D7*B6 -> 0.4844052 | D6: =C6*1000000 -> 484405.2 | E6: =D6/'1_Assumptions'!C10 -> 1214.0481 | F6: Only if interviews show clear switch from timer irrigators
A8: Also stress-test SAM channel % (A07)
A9: Alt A07 | B9: 0.08 | C9: Alt SAM CNY million | D9: ='2_TAM_SAM_SOM_Chain'!D5*'1_Assumptions'!C6*'1_Assumptions'!C7*B9 -> 10.76456 | E9: Alt SOM @ active rate | F9: =D9*'1_Assumptions'!C9 -> 0.2152912
A11: How to answer supervisor live
A12: Change the capture assumption in 1_Assumptions!C9: main SOM, base sensitivity and alternative-channel SOM all update. The 1% and 3% cases are stress tests, not statistical confidence bounds.

Sheet 4_BottomUp_Check
A1: BOTTOM-UP SANITY CHECK (student desk-pot path) — reconcile with top-down SOM
A3: Step | B3: Description | C3: Formula text (update if formula edited) | D3: Result | E3: Unit | F3: Source IDs | G3: Note
A4: 1 | B4: HE students (persons) | C4: ='1_Assumptions'!C14*10000 | D4: ='1_Assumptions'!C14*10000 -> 38912600 | E4: persons | F4: B01 | G4: MOE 2024
A5: 2 | B5: Student plant owners (national theoretical) | C5: =D4*'1_Assumptions'!C15 | D5: =D4*'1_Assumptions'!C15 -> 7782520 | E5: persons | F5: B02 | G5: Ownership prior UNVERIFIED
A6: 3 | B6: National student buyers open to smart device (theoretical annual) | C6: =D5*'1_Assumptions'!C16 | D6: =D5*'1_Assumptions'!C16 -> 622601.6 | E6: persons | F6: B03 | G6: This is NOT Year-1 SOM — too wide
A7: 4 | B7: Theoretical student-segment revenue if all converted @ ASP | C7: =D6*'1_Assumptions'!C10/1000000 | D7: =D6*'1_Assumptions'!C10/1000000 -> 248.41804 | E7: CNY million | F7: A09 | G7: Upper-bound story only
A8: 5 | B8: Year-1 REACHABLE students (channel capacity) | C8: ='1_Assumptions'!C17 | D8: ='1_Assumptions'!C17 -> 80000 | E8: persons | F8: B04 | G8: Campus+content capacity
A9: 6 | B9: Reachable plant owners | C9: =D8*'1_Assumptions'!C15 | D9: =D8*'1_Assumptions'!C15 -> 16000 | E9: persons | F9: B02,B04
A10: 7 | B10: Bottom-up Year-1 units | C10: =D9*'1_Assumptions'!C18 | D10: =D9*'1_Assumptions'!C18 -> 240 | E10: units | F10: B05 | G10: Direct conversion among reachable plant owners; 8% is not an extra funnel factor.
A11: 8 | B11: Bottom-up Year-1 SOM (CNY million) | C11: =D10*'1_Assumptions'!C10/1000000 | D11: =D10*'1_Assumptions'!C10/1000000 -> 0.09576 | E11: CNY million | F11: A09 | G11: Compare to top-down SOM D9
A13: Reconciliation
A14: Top-down SOM (CNY million) | B14: ='2_TAM_SAM_SOM_Chain'!D9 -> 0.3229368
A15: Bottom-up SOM (CNY million) | B15: =D11 -> 0.09576
A16: Ratio bottom-up / top-down | B16: =IF(B14=0,"n/a",B15/B14) -> 0.29652861
A17: Not an independent validation: student-only bottom-up is narrower than student + young-worker top-down. Both depend on unverified assumptions. The ratio is diagnostic, not proof of agreement; a >10x gap requires explicit review.
A19: Reconciliation detail | B19: Metric / explanation
A20: Gap | B20: Top-down less student-only bottom-up | C20: =(B14-B15)*1000000 | D20: =(B14-B15)*1000000 -> 227176.8 | E20: CNY | G20: Scope and assumptions differ; not evidence of worker sales.
A21: Multiple | B21: Top-down / student-only bottom-up | C21: =IF(B15=0,"n/a",B14/B15) | D21: =IF(B15=0,"n/a",B14/B15) -> 3.3723559 | E21: times | G21: Diagnostic only; no acceptance threshold.
A22: Scope | B22: Top-down: students + young professionals; bottom-up: students only.
A23: Decision | B23: Keep the 2% top-down case as the market scenario and the student-only case as a separate plausibility check. Neither is an actual sales result.
A24: Next step | B24: Validate campus reach and direct paid conversion; quantify young-worker channels separately. Do not manufacture worker sales to force equality.
A26: Gap review | B26: =IF(OR(B14<=0,B15<=0),"Review zero or missing inputs",IF(OR(B14/B15>10,B15/B14>10),">10x gap: revisit scope, reach and capture assumptions","Below 10x; scope and assumptions still need explanation")) -> Below 10x; scope and assumptions still need explanation

Sheet 5_Sources
A1: ID | B1: User-supplied external claim | C1: Source | D1: URL | E1: Permitted use | F1: Limit / confidence
A2: S01 | B2: China Smart Planters: US$87.1M in 2030; CAGR 5.3% (2024-2030) | C2: GIA / GII public abstract | D2: https://www.giiresearch.com/report/go1739256-smart-planters.html | E2: Device TAM proxy; back-calculate 2024 | F2: Medium; forecast and adjacent-category proxy, not our sales.
A3: S02 | B3: 2024 indoor foliage plants: CNY135亿元; tropical/specialty about 30% | C3: China Flower Association / forestry portal | D3: https://www.forestry.gov.cn/lyj/1/gghhmmcy/20250328/617790.html | E3: CONTEXT only | F3: Plant spending, not device TAM.
A4: S03 | B4: 2024 flowers: near CNY2200亿元; online about CNY1200亿元 / 54.5% | C4: China Flower Association retail branch | D4: https://www.chinahhxh.com/hhxh/magazineNewsDetail.html?contentId=1234&id=73&subCategoryId=15 | E4: CONTEXT / channel direction only | F4: Does not establish device adoption or team reach.
A5: S04 | B5: 2024 indoor plants: CNY222.23亿元 | C5: Beizhes, cited by Gelonghui | D5: https://www.gelonghui.com/p/2427468 | E5: CONTEXT only | F5: Medium; secondary citation, broad plant category.
A6: S05 | B6: 2024 ordinary + vocational undergraduate/college students: 3891.26万人 | C6: MOE 2024 statistical bulletin | D6: http://www.moe.gov.cn/jyb_sjzl/sjzl_fztjgb/202506/t20250611_1193760.html | E6: Bottom-up national student pool | F6: User-supplied official data; excludes worker pool.
A7: S06 | B7: Green-home preference about 50.29% in 18-35 sample | C7: Fudan Development Institute | D7: https://fddi.fudan.edu.cn/54/c7/c19047a742599/page.htm | E7: Preference context only | F7: Not ownership, purchase conversion or national penetration.
A8: S07 | B8: White-collar and student buyers; self-watering/lazy pots popular | C8: Consumer Daily / JD consumption coverage | D8: http://www.xfrb.com.cn/article/council/16452445152521.html | E8: ICP and substitutes context | F8: Platform observations, not national shares.
A9: S08 | B9: Yimitian-like third-party band about CNY399-499 | C9: User-supplied price band; official entry | D9: http://www.ymitian.cn/chanpin4/91.html | E9: ASP reference; base translation uses 399 | F9: Medium; channel variation; not Green Sight price; official entry is not proof of current band.
A10: S09 | B10: Xiaomi Flower Monitor about CNY49; monitoring only | C10: User-supplied official-price reference | D10: https://www.mi.com/flowermonitor | E10: Lower-feature price comparison | F10: Availability/current price not rechecked; no actuation.
A11: S10 | B11: Wi-Fi timer/remote irrigators about CNY40-50+ | C11: User-supplied aggregator example | D11: https://www.tianmaocn.com/item/oo8wN2fBv88mQevHJn.html | E11: Low-cost substitute context | F11: Low; aggregate listing; no sales-volume or market-share inference.

Sheet 6_A1_Slide_Snippets
A1: Draft lines for Assessment 1 Slide 2 (Problem & Market Opportunity)
A3: English (A1 deck)
A4: Green Sight AI is a continuing prototype with no paid revenue or observed conversion rate. The China smart-planter proxy uses the 2024 baseline. SAM filters and Year-1 capture are explicitly unverified planning assumptions. Use the linked figures below with the 1% / 2% / 3% sensitivity, not as actual traction.
A6: Linked scenario figures - disclose assumptions and baseline year
A7: TAM CNY million | B7: ='2_TAM_SAM_SOM_Chain'!D5 -> 460.02393
A8: SAM CNY million | B8: ='2_TAM_SAM_SOM_Chain'!D7 -> 16.14684
A9: SOM CNY million (active rate) | B9: ='2_TAM_SAM_SOM_Chain'!D9 -> 0.3229368
A10: SOM CNY | B10: ='2_TAM_SAM_SOM_Chain'!D10 -> 322936.8
A11: Illustrative units | B11: ='2_TAM_SAM_SOM_Chain'!D11 -> 809.36541
A13: Chinese (Evidence Hub / oral checkpoint)
A14: Green Sight AI目前仍是原型，无付费收入或真实转化率。以2024中国智能花盆市场为设备代理；SAM的65%室内占比、45%ICP占比、12%渠道可达比例和SOM的2%捕获率均为UNVERIFIED假设。植物零售额仅作背景。学生bottom-up是不同范围的对照，不是对预测的独立验证。
